[
    {
        "display_name": "Dashboard",
        "route": "/he-thong",
        "icon": "bx bx-category-alt"
    },
    {
        "display_name": "Bệnh nhân mới",
        "route": "/he-thong/benh-nhan-moi",
        "icon": "bx bx-user-pin"
    },
    {
        "display_name": "Quản lý bác sĩ",
        "route": "/he-thong/quan-ly-bac-si",
        "icon": "bx bx-package"
    },
    {
        "display_name": "Quản lý phòng khám",
        "route": "/he-thong/quan-ly-phong-kham",
        "icon": "bx bx-cart"
    },
    {
        "display_name": "Quản lý kế hoạch khám bệnh",
        "route": "/he-thong/quan-ly-ke-hoach-kham-benh",
        "icon": "bx bx-bar-chart-alt"
    }
]